canfork/__init__.py
canfork-0.1.0.dist-info/metadata.json
canfork-0.1.0.dist-info/METADATA
canfork-0.1.0.dist-info/DESCRIPTION.rst
canfork-0.1.0.dist-info/entry_points.txt
canfork-0.1.0.dist-info/top_level.txt
canfork-0.1.0.dist-info/RECORD
canfork-0.1.0.dist-info/WHEEL
