Metadata-Version: 2.0
Name: canfork
Version: 0.1.0
Summary: Guess whether a process can fork depending on VSZ.
Home-page: https://github.com/krallin/canfork
Author: Thomas Orozco
Author-email: thomas@orozco.fr
License: ISCL
Keywords: canfork
Platform: UNKNOWN
Classifier: Development Status :: 2 - Pre-Alpha
Classifier: Intended Audience :: Developers
Classifier: License :: OSI Approved :: ISC License (ISCL)
Classifier: Natural Language :: English
Classifier: Programming Language :: Python :: 2
Classifier: Programming Language :: Python :: 2.6
Classifier: Programming Language :: Python :: 2.7
Classifier: Programming Language :: Python :: 3
Classifier: Programming Language :: Python :: 3.3
Classifier: Programming Language :: Python :: 3.4
Classifier: Programming Language :: Python :: 3.5
